nations/__init__.py
nations/main.py
nations-0.0.2.dist-info/METADATA
nations-0.0.2.dist-info/WHEEL
nations-0.0.2.dist-info/top_level.txt
nations-0.0.2.dist-info/RECORD
